{
    "Initial_routing": [
        [
            1,
            2
        ],
        [
            2,
            3
        ],
        [
            3,
            10
        ],
        [
            10,
            23
        ],
        [
            23,
            24
        ]
    ],
    "Final_routing": [
        [
            1,
            2
        ],
        [
            2,
            3
        ],
        [
            3,
            10
        ],
        [
            10,
            23
        ],
        [
            23,
            24
        ]
    ],
    "Properties": {
        "Waypoint": {
            "startNode": 1,
            "finalNode": 4,
            "waypoint": 10
        },
        "LoopFreedom": {
            "startNode": 1
        },
        "Reachability": {
            "startNode": 1,
            "finalNode": 4
        }
    }
}