{
    "Initial_routing": [
        [
            0,
            7
        ],
        [
            7,
            24
        ],
        [
            24,
            32
        ],
        [
            32,
            37
        ],
        [
            37,
            38
        ]
    ],
    "Final_routing": [
        [
            0,
            6
        ],
        [
            6,
            7
        ],
        [
            7,
            24
        ],
        [
            24,
            32
        ],
        [
            32,
            37
        ],
        [
            37,
            38
        ]
    ],
    "Properties": {
        "Waypoint": {
            "startNode": 0,
            "finalNode": 5,
            "waypoint": 32
        },
        "LoopFreedom": {
            "startNode": 0
        },
        "Reachability": {
            "startNode": 0,
            "finalNode": 5
        }
    }
}