{
    "Initial_routing": [
        [
            0,
            5
        ],
        [
            5,
            9
        ]
    ],
    "Final_routing": [
        [
            0,
            5
        ],
        [
            5,
            7
        ],
        [
            7,
            9
        ]
    ],
    "Properties": {
        "Waypoint": {
            "startNode": 0,
            "finalNode": 9,
            "waypoint": 5
        },
        "LoopFreedom": {
            "startNode": 0
        },
        "Reachability": {
            "startNode": 0,
            "finalNode": 9
        }
    }
}