{
    "Initial_routing": [
        [
            179,
            180
        ],
        [
            180,
            181
        ],
        [
            181,
            182
        ],
        [
            182,
            183
        ],
        [
            183,
            184
        ],
        [
            184,
            713
        ],
        [
            713,
            714
        ],
        [
            714,
            715
        ],
        [
            715,
            716
        ]
    ],
    "Final_routing": [
        [
            179,
            180
        ],
        [
            180,
            181
        ],
        [
            181,
            182
        ],
        [
            182,
            183
        ],
        [
            183,
            184
        ],
        [
            184,
            713
        ],
        [
            713,
            714
        ],
        [
            714,
            715
        ],
        [
            715,
            716
        ]
    ],
    "Properties": {
        "Waypoint": {
            "startNode": 179,
            "finalNode": 8,
            "waypoint": 714
        },
        "LoopFreedom": {
            "startNode": 179
        },
        "Reachability": {
            "startNode": 179,
            "finalNode": 8
        }
    }
}