{
    "Initial_routing": [
        [
            1,
            126
        ],
        [
            126,
            127
        ]
    ],
    "Final_routing": [
        [
            1,
            91
        ],
        [
            91,
            94
        ],
        [
            94,
            126
        ],
        [
            126,
            127
        ]
    ],
    "Properties": {
        "Waypoint": {
            "startNode": 1,
            "finalNode": 127,
            "waypoint": 126
        },
        "LoopFreedom": {
            "startNode": 1
        },
        "Reachability": {
            "startNode": 1,
            "finalNode": 127
        }
    }
}