{
    "Initial_routing": [
        [
            11,
            74
        ],
        [
            74,
            75
        ],
        [
            75,
            81
        ]
    ],
    "Final_routing": [
        [
            11,
            74
        ],
        [
            74,
            75
        ],
        [
            75,
            81
        ]
    ],
    "Properties": {
        "Waypoint": {
            "startNode": 11,
            "finalNode": 2,
            "waypoint": 75
        },
        "LoopFreedom": {
            "startNode": 11
        },
        "Reachability": {
            "startNode": 11,
            "finalNode": 2
        }
    }
}